MANIFEST.in
README.md
requirements.txt
setup.cfg
setup.py
dnsbl_checker/__init__.py
dnsbl_checker/checker.py
dnsbl_checker/cli.py
dnsbl_checker/providers.py
dnsbl_checker/saver.py
dnsbl_checker/telegram.py
dnsbl_checker/utils.py
dnsbl_checker.egg-info/PKG-INFO
dnsbl_checker.egg-info/SOURCES.txt
dnsbl_checker.egg-info/dependency_links.txt
dnsbl_checker.egg-info/entry_points.txt
dnsbl_checker.egg-info/requires.txt
dnsbl_checker.egg-info/top_level.txt