Metadata-Version: 1.0
Name: dnsbl-checker
Version: 0.0.3
Summary: Asynchronous script for monitoring dns blacklists
Home-page: https://github.com/VadimZhyvyloKS/dnsbl-checker
Author: Vadim Zhyvylo
Author-email: jyvylo5@gmail.com
License: MIT
Keywords: dns blacklist dnsbl async asynchronous check
Platform: UNKNOWN
